dice.py
distribution.py
eote_dice.py
eote_dice-1.2.0.data/scripts/eote_dice.py
eote_dice-1.2.0.dist-info/LICENSE.txt
eote_dice-1.2.0.dist-info/METADATA
eote_dice-1.2.0.dist-info/WHEEL
eote_dice-1.2.0.dist-info/entry_points.txt
eote_dice-1.2.0.dist-info/top_level.txt
eote_dice-1.2.0.dist-info/RECORD
