Metadata-Version: 2.1
Name: eote-dice
Version: 1.2.0
Summary: Utility for analyzing Star Wars Edge of the Empire (EotE) dice rolls.
Home-page: https://github.com/johnthagen/eote-dice
Author: John Hagen
Author-email: johnthagen@gmail.com
License: MIT
Keywords: star wars EotE dice role-playing
Platform: UNKNOWN
Classifier: Development Status :: 4 - Beta
Classifier: Environment :: Console
Classifier: Intended Audience :: End Users/Desktop
Classifier: License :: OSI Approved :: MIT License
Classifier: Operating System :: OS Independent
Classifier: Programming Language :: Python
Classifier: Programming Language :: Python :: 3
Classifier: Programming Language :: Python :: 3 :: Only
Classifier: Programming Language :: Python :: 3.5
Classifier: Programming Language :: Python :: 3.6
Classifier: Programming Language :: Python :: 3.7
Classifier: Programming Language :: Python :: 3.8
Classifier: Programming Language :: Python :: Implementation :: CPython
Classifier: Programming Language :: Python :: Implementation :: PyPy
Classifier: Topic :: Games/Entertainment :: Role-Playing
Requires-Dist: colorama (>=0.3.5)
